Metadata-Version: 2.1
Name: stoq-framework
Version: 3.0.1
Summary: A framework for simplifying analysis.
Home-page: https://github.com/PUNCH-Cyber/stoq
Author: Marcus LaFerrera
Author-email: marcus@punchcyber.com
License: Apache License 2.0
Keywords: malware-analysis,malware-analyzer,malware-detection,framework,automation
Platform: UNKNOWN
Classifier: Development Status :: 4 - Beta
Classifier: Intended Audience :: Information Technology
Classifier: Intended Audience :: Developers
Classifier: Intended Audience :: System Administrators
Classifier: Topic :: Security
Classifier: Topic :: Utilities
Classifier: License :: OSI Approved :: Apache Software License
Classifier: Programming Language :: Python :: 3.6
Classifier: Programming Language :: Python :: 3.7
Classifier: Programming Language :: Python :: 3.8
Requires-Python: >=3.6
